musicraft/__init__.py
musicraft/__main__.py
musicraft/shared.py
musicraft/abcraft/__init__.py
musicraft/abcraft/external.py
musicraft/abcraft/midiplayer.py
musicraft/abcraft/score.py
musicraft/abcraft/scrap.py
musicraft/abcraft/syntax.py
musicraft/freqraft/__init__.py
musicraft/freqraft/freq_view.py
musicraft/freqraft/pitch_view.py
musicraft/freqraft/terpsichore.py
musicraft/pyraft/__init__.py
musicraft/pyraft/external.py
musicraft/pyraft/html_view.py
musicraft/pyraft/image_view.py
musicraft/pyraft/syntax.py
musicraft/pyraft/text_view.py
musicraft/raft/__init__.py
musicraft/raft/editbook.py
musicraft/raft/editor.py
musicraft/raft/external.py
musicraft/raft/find.py
musicraft/util/__init__.py
musicraft/util/arghandler.py
musicraft/util/other_clef.py
musicraft/util/toFclef.py
musicraft-1.0.10.data/data/share/musicraft/Linux/bin/README.txt
musicraft-1.0.10.data/data/share/musicraft/Linux/bin/abc2abc
musicraft-1.0.10.data/data/share/musicraft/Linux/bin/abc2midi
musicraft-1.0.10.data/data/share/musicraft/Linux/bin/abcm2ps
musicraft-1.0.10.data/data/share/musicraft/Linux/bin/rsvg-convert
musicraft-1.0.10.data/data/share/musicraft/Linux/bin/xml2abc.py
musicraft-1.0.10.data/data/share/musicraft/OSX/bin/abc2abc
musicraft-1.0.10.data/data/share/musicraft/OSX/bin/abc2midi
musicraft-1.0.10.data/data/share/musicraft/OSX/bin/abc2prt
musicraft-1.0.10.data/data/share/musicraft/OSX/bin/abcm2ps
musicraft-1.0.10.data/data/share/musicraft/OSX/bin/abcmatch
musicraft-1.0.10.data/data/share/musicraft/OSX/bin/abcpp
musicraft-1.0.10.data/data/share/musicraft/OSX/bin/mftext
musicraft-1.0.10.data/data/share/musicraft/OSX/bin/midi2abc
musicraft-1.0.10.data/data/share/musicraft/OSX/bin/midicopy
musicraft-1.0.10.data/data/share/musicraft/OSX/bin/yaps
musicraft-1.0.10.data/data/share/musicraft/Windows/abcm2ps-8.14.4/COPYING
musicraft-1.0.10.data/data/share/musicraft/Windows/abcm2ps-8.14.4/INSTALL
musicraft-1.0.10.data/data/share/musicraft/Windows/abcm2ps-8.14.4/README.md
musicraft-1.0.10.dist-info/licenses/LICENSE.txt
musicraft-1.0.10.dist-info/METADATA
musicraft-1.0.10.dist-info/WHEEL
musicraft-1.0.10.dist-info/top_level.txt
musicraft-1.0.10.dist-info/RECORD
