Metadata-Version: 2.4
Name: MusicRaft
Version: 1.0.10
Summary: GUI for abcplus music notation.
Home-page: https://gitlab.com/papahippo/MusicRaft
Author: Larry Myerscough
Author-email: hippostech@gmail.com
License: LICENSE.txt
License-File: LICENSE.txt
Requires-Dist: python-rtmidi
Requires-Dist: mido>=1.2.0
Requires-Dist: lxml
Requires-Dist: numpy
Requires-Dist: pyqt5
Requires-Dist: pyqtwebengine
Requires-Dist: pdfrw
Requires-Dist: ghostscript
Dynamic: author
Dynamic: author-email
Dynamic: description
Dynamic: description-content-type
Dynamic: home-page
Dynamic: license
Dynamic: license-file
Dynamic: requires-dist
Dynamic: summary
